{
  "air_freight": [
    {
      "label": "Marketplace Rate",
      "value": "marketplace_rate"
    }
  ],
  "ftl_freight": [
    {
      "label": "Marketplace Rate",
      "value": "marketplace_rate"
    }
  ],
  "ltl_freight": [
    {
      "label": "Marketplace Rate",
      "value": "marketplace_rate"
    }
  ],
  "fcl_freight_local": [
    {
      "label": "Marketplace Rate",
      "value": "marketplace_rate"
    },
    {
      "label": "Cogo Assured Rate",
      "value": "cogo_assured_rate"
    }
  ],
  "air_freight_local": [
    {
      "label": "Marketplace Rate",
      "value": "marketplace_rate"
    }
  ],
  "trailer_freight": [
    {
      "label": "Marketplace Rate",
      "value": "marketplace_rate"
    }
  ],
  "haulage_freight": [
    {
      "label": "Marketplace Rate",
      "value": "marketplace_rate"
    },
    {
      "label": "Cogo Assured Rate",
      "value": "cogo_assured_rate"
    }
  ],
  "fcl_freight": [
    {
      "label": "Marketplace Rate",
      "value": "marketplace_rate"
    },
    {
      "label": "Cogo Assured Rate",
      "value": "cogo_assured_rate"
    }
  ],
  "lcl_freight": [
    {
      "label": "Marketplace Rate",
      "value": "marketplace_rate"
    }
  ],
  "fcl_customs": [
    {
      "label": "Marketplace Rate",
      "value": "marketplace_rate"
    }
  ],
  "lcl_customs": [
    {
      "label": "Marketplace Rate",
      "value": "marketplace_rate"
    }
  ],
  "air_customs": [
    {
      "label": "Marketplace Rate",
      "value": "marketplace_rate"
    }
  ],
  "rail_domestic_freight": [
    {
      "label": "Marketplace Rate",
      "value": "marketplace_rate"
    }
  ]
}
