{
    "employee_detail": {
        "id": "dfca5d91-8906-d146-2970-202eace33a66",
        "name": "Hrishikesh Kulkarni",
        "name_title": "",
        "personal_email": "hk@gmail.com",
        "cogoport_email": "hk@cogoport.com",
        "designation": "COO",
        "mobile_number": "9821197245",
        "mobile_country_code": "+91",
        "date_of_birth": null,
        "gender": "Male",
        "present_address": null,
        "permanent_address": null,
        "employee_code": "COGO-0563",
        "hiring_manager_id": "dfca5d91-8906-d146-2970-202eace33a357",
        "hr_id": "dd578df3-a8f8-c9f6-1dae-d9d6da9d5791",
        "hrbp_id": "55c92e97-4937-4e80-a09d-7be550221515",
        "office_location": "Mumbai",
        "relation_type": "",
        "relation_person_name": "",
        "emergency_contact_details": null,
        "passport_size_photo_url": "",
        "employee_education_details": null,
        "employee_experience_details": null,
        "policies_data": null,
        "date_of_joining": "2022-04-01T00:00:00.000Z",
        "department": "Management",
        "user_id": "7c6c1fe7-4a4d-4f3a-b432-b05ffdec3b44",
        "status": "active",
        "remarks": null,
        "created_at": "2023-06-07T10:06:00.000Z",
        "updated_at": "2023-09-06T11:49:47.977Z",
        "jira_user_id": null,
        "reporting_manager_id": "54789fa9-1bae-ad2d-385d-5878eb0af5ac",
        "role_id": "98536761-0f8c-296c-c115-c6288e360a3b",
        "employee_status": "confirmed",
        "employee_type": "Full Time",
        "pi": "Operator",
        "li": 310,
        "resignation_date": "2023-09-05T06:11:11.969Z",
        "last_working_date": "2023-09-28T09:06:08.203Z",
        "settlement_month": "",
        "job_segment": "Non-Commercial",
        "reporting_country_id": null,
        "share_company_policies": false,
        "is_offer_letter_applicable": false,
        "cfpl_joining_date": null,
        "pay_band_id": null,
        "employee_tags": {},
        "payroll_country_id": null,
        "reporting_location_id": "9094e4e9-0ddd-4c1c-83ce-f69e1a16f5c0",
        "company_id": "f2753d8d-308e-406c-bb33-a4fdb585a360",
        "date_of_confirmation": null,
        "role_name": "HR Associate Manager - HRBP",
        "hrbp_name": "Dharmjeet Kumar Singh",
        "reporting_manager_name": "Harsh Thakur"
    },
    "modified_employee_detail": {},
    "processed_employee_detail": {
        "first_name": "Hrishikesh",
        "last_name": "Kulkarni",
        "age_in_organization": "1 Year 5 Months 5 Days"
    },
    "documents": [],
    "personal_details": null
}, 

{
    "employee_detail": {
        "id": "dfca5d91-8906-d146-2970-202eace33a66",
        "name": "Hrishikesh Kulkarni",
        "name_title": "",
        "personal_email": "hk@gmail.com",
        "cogoport_email": "hk@cogoport.com",
        "designation": "COO",
        "mobile_number": "9821197245",
        "mobile_country_code": "+91",
        "date_of_birth": null,
        "gender": "Male",
        "present_address": {
            "city": "Gurugram ",
            "state": "Haryana ",
            "address": "Global Stay PG Kanhai Villege Sec 45, Gurugram, Haryana ",
            "country": "India",
            "pincode": "122003"
        },
        "permanent_address": {
            "city": "Almora",
            "state": "Uttarakhand ",
            "address": "Villege Galigaon Post Khatagaon Syaldey Almora Uttarakhand ",
            "country": "India",
            "pincode": "263661"
        },
        "employee_code": "COGO-0563",
        "hiring_manager_id": "dfca5d91-8906-d146-2970-202eace33a357",
        "hr_id": "dd578df3-a8f8-c9f6-1dae-d9d6da9d5791",
        "hrbp_id": "55c92e97-4937-4e80-a09d-7be550221515",
        "office_location": "Mumbai",
        "relation_type": "",
        "relation_person_name": "",
        "emergency_contact_details": null,
        "passport_size_photo_url": "",
        "employee_education_details": null,
        "employee_experience_details": null,
        "policies_data": null,
        "date_of_joining": "2022-04-01T00:00:00.000Z",
        "department": "Management",
        "user_id": "7c6c1fe7-4a4d-4f3a-b432-b05ffdec3b44",
        "status": "active",
        "remarks": null,
        "created_at": "2023-06-07T10:06:00.000Z",
        "updated_at": "2023-09-06T11:49:47.977Z",
        "jira_user_id": null,
        "reporting_manager_id": "54789fa9-1bae-ad2d-385d-5878eb0af5ac",
        "role_id": "98536761-0f8c-296c-c115-c6288e360a3b",
        "employee_status": "confirmed",
        "employee_type": "Full Time",
        "pi": "Operator",
        "li": 310,
        "resignation_date": "2023-09-05T06:11:11.969Z",
        "last_working_date": "2023-09-28T09:06:08.203Z",
        "settlement_month": "",
        "job_segment": "Non-Commercial",
        "reporting_country_id": null,
        "share_company_policies": false,
        "is_offer_letter_applicable": false,
        "cfpl_joining_date": null,
        "pay_band_id": null,
        "employee_tags": {},
        "payroll_country_id": null,
        "reporting_location_id": "9094e4e9-0ddd-4c1c-83ce-f69e1a16f5c0",
        "company_id": "f2753d8d-308e-406c-bb33-a4fdb585a360",
        "date_of_confirmation": null,
        "role_name": "HR Associate Manager - HRBP",
        "hrbp_name": "Dharmjeet Kumar Singh",
        "reporting_manager_name": "Harsh Thakur"
    },
    "modified_employee_detail": {},
    "processed_employee_detail": {
        "first_name": "Hrishikesh",
        "last_name": "Kulkarni",
        "age_in_organization": "1 Year 5 Months 5 Days",
        "date_of_joining": "01/04/2022"
    },
    "other_documents": [
        {
            "pan_card": {
                "id": "680e8dda-d191-41eb-b38c-4f932419fbbb",
                "employee_detail_id": "dfca5d91-8906-d146-2970-202eace33a66",
                "document_type": "pan_card",
                "document_number": null,
                "document_url": null,
                "status": "active",
                "signed_document_url": null,
                "adobe_agreement_id": null,
                "created_at": "2023-09-10T14:13:08.970Z",
                "updated_at": "2023-09-10T14:13:08.970Z",
                "rejection_reason": null
            }
        },
        {
            "aadhaar_card": {
                "id": "514bdf2e-3931-46c3-a2e7-94c2fcba335b",
                "employee_detail_id": "dfca5d91-8906-d146-2970-202eace33a66",
                "document_type": "aadhaar_card",
                "document_number": null,
                "document_url": null,
                "status": "active",
                "signed_document_url": null,
                "adobe_agreement_id": null,
                "created_at": "2023-09-10T14:12:50.418Z",
                "updated_at": "2023-09-10T14:12:50.418Z",
                "rejection_reason": null
            }
        }
    ],
    "signed_documents": [
        "Employment Agreement": {
            "id": "48651fe8-7fa4-4025-a3cf-609c0829070c",
            "employee_detail_id": "dfca5d91-8906-d146-2970-202eace33a66",
            "name": "Employment Agreement",
            "document_url": null,
            "status": "accepted",
            "signed_document_url": null,
            "adobe_agreement_id": null,
            "created_at": "2023-09-10T14:25:06.504Z",
            "updated_at": "2023-09-10T14:25:06.504Z"
        },
        {
            "Employment Confirmation Letter": {
                "id": "c827ee8e-6b5a-40e0-8000-402f711a5772",
                "employee_detail_id": "dfca5d91-8906-d146-2970-202eace33a66",
                "name": "Employment Confirmation Letter",
                "document_url": null,
                "status": "accepted",
                "signed_document_url": null,
                "adobe_agreement_id": null,
                "created_at": "2023-09-10T14:25:46.567Z",
                "updated_at": "2023-09-10T14:25:46.567Z"
            }
        }
    ],
    "personal_details": {
        "id": "fbd38ee8-4aed-46f9-a593-8585db542b22",
        "employee_detail_id": "dfca5d91-8906-d146-2970-202eace33a66",
        "about": "This is about.",
        "marital_status": "married",
        "spouse_details": null,
        "family_details": {
            "Dependent": "No",
            "father_name": "testname father",
            "mother_name": "testname mother",
            "guardian_name": "",
            "father_mobile_number": "9873259293",
            "mother_mobile_number": "2345235434",
            "family_physician_name": "",
            "guardian_mobile_number": "",
            "are_parents_senior_citizen": "No",
            "father_mobile_country_code": "+91",
            "mother_mobile_country_code": "+91",
            "guardian_mobile_country_code": "",
            "family_physician_country_code": "",
            "family_physician_mobile_number": ""
        },
        "created_at": "2023-09-10T13:37:50.215Z",
        "updated_at": "2023-09-10T13:37:50.215Z",
        "cover_photo_url": null,
        "blood_group": "A+",
        "disability_level": "None",
        "allergies": "None",
        "alternate_mobile_number": "9238476545",
        "alternate_mobile_country_code": "+91"
    },
    "job_history": [
        {
            "id": "2fb12c84-2c3d-460e-a598-710be4f88979",
            "employee_detail_id": "dfca5d91-8906-d146-2970-202eace33a66",
            "effective_from": "2023-09-10T14:31:12.995Z",
            "effective_to": null,
            "role_id": null,
            "department_id": null,
            "manager_id": null,
            "hrbp_id": null,
            "company_id": null,
            "reporting_location_id": null,
            "confirmation_date": null,
            "confirmation_due_date": null,
            "employee_status": "Fulltime",
            "confirmed_by": null,
            "entry_status": "",
            "created_at": "2023-09-10T14:31:12.995Z",
            "updated_at": "2023-09-10T14:31:12.995Z"
        },
        {
            "id": "ae767ee4-8ce8-4a75-b369-91069ac32ead",
            "employee_detail_id": "dfca5d91-8906-d146-2970-202eace33a66",
            "effective_from": "2021-09-10T14:31:12.995Z",
            "effective_to": "2023-09-10T14:31:12.995Z",
            "role_id": null,
            "department_id": null,
            "manager_id": null,
            "hrbp_id": null,
            "company_id": null,
            "reporting_location_id": null,
            "confirmation_date": null,
            "confirmation_due_date": null,
            "employee_status": "probation",
            "confirmed_by": null,
            "entry_status": "",
            "created_at": "2023-09-10T14:31:30.041Z",
            "updated_at": "2023-09-10T14:31:30.041Z"
        }
    ]
}